kissllm/__init__.py
kissllm/client.py
kissllm/exceptions.py
kissllm/io.py
kissllm/stream.py
kissllm/tools.py
kissllm/utils.py
kissllm/mcp/__init__.py
kissllm/mcp/manager.py
kissllm/observation/__init__.py
kissllm/observation/base.py
kissllm/observation/decorators.py
kissllm/observation/langfuse.py
kissllm/providers/__init__.py
kissllm/providers/base.py
kissllm/providers/openai.py
kissllm-0.1.0.dist-info/licenses/LICENSE
kissllm-0.1.0.dist-info/METADATA
kissllm-0.1.0.dist-info/WHEEL
kissllm-0.1.0.dist-info/top_level.txt
kissllm-0.1.0.dist-info/RECORD
