Metadata-Version: 2.4
Name: kissllm
Version: 0.1.0
Summary: Simple Smart LLM SDK
Requires-Python: >=3.12
License-File: LICENSE
Requires-Dist: langfuse>=2.59.3
Requires-Dist: openai>=1.63.0
Requires-Dist: mcp>=1.16.0
Requires-Dist: asyncio
Requires-Dist: pyyaml>=6.0.2
Dynamic: license-file
